qwertyasdfgh/__init__.py
qwertyasdfgh/demo.py
testmoltobello-0.0.1.dist-info/LICENSE
testmoltobello-0.0.1.dist-info/METADATA
testmoltobello-0.0.1.dist-info/WHEEL
testmoltobello-0.0.1.dist-info/top_level.txt
testmoltobello-0.0.1.dist-info/RECORD
