Metadata-Version: 2.1
Name: testmoltobello
Version: 0.0.1
Summary: this is a test
Home-page: UNKNOWN
Author: gfrawing
Author-email: federico@gmail.com
License: UNKNOWN
Keywords: test
Platform: UNKNOWN
Classifier: Development Status :: 1 - Planning
Classifier: Intended Audience :: Developers
Classifier: Programming Language :: Python :: 3
Classifier: Operating System :: Unix
Classifier: Operating System :: MacOS :: MacOS X
Classifier: Operating System :: Microsoft :: Windows
License-File: LICENSE
